django_emaillog_backend/__init__.py
django_emaillog_backend/backends.py
django_emaillog_backend-0.1.2.dist-info/LICENSE
django_emaillog_backend-0.1.2.dist-info/METADATA
django_emaillog_backend-0.1.2.dist-info/WHEEL
django_emaillog_backend-0.1.2.dist-info/top_level.txt
django_emaillog_backend-0.1.2.dist-info/RECORD
