Metadata-Version: 2.1
Name: django-emaillog-backend
Version: 0.1.2
Summary: Django email backend that writes messages to logger instead of sending them by SMTP.
Home-page: http://github.com/albertoalcolea/django-emaillog-backend
Author: Alberto Alcolea
Author-email: me@albertoalcolea.com
License: MIT
Project-URL: Source, http://github.com/albertoalcolea/django-emaillog-backend
Keywords: django mail,django log,django logger,django mail backend,django mail log backend,django mail logger backend,django plugin
Classifier: Development Status :: 5 - Production/Stable
Classifier: Environment :: Plugins
Classifier: Framework :: Django
Classifier: Framework :: Django :: 1.11
Classifier: Framework :: Django :: 2.2
Classifier: Framework :: Django :: 3.2
Classifier: Framework :: Django :: 4.0
Classifier: Intended Audience :: Developers
Classifier: License :: OSI Approved :: MIT License
Classifier: Operating System :: OS Independent
Classifier: Topic :: Software Development :: Libraries :: Python Modules
Classifier: Programming Language :: Python
Classifier: Programming Language :: Python :: 2
Classifier: Programming Language :: Python :: 2.7
Classifier: Programming Language :: Python :: 3
Classifier: Programming Language :: Python :: 3.4
Classifier: Programming Language :: Python :: 3.5
Classifier: Programming Language :: Python :: 3.6
Classifier: Programming Language :: Python :: 3.7
Classifier: Programming Language :: Python :: 3.8
Classifier: Programming Language :: Python :: 3.9
Classifier: Programming Language :: Python :: 3.10
License-File: LICENSE
Requires-Dist: django (>=1.2)
Provides-Extra: dev
Requires-Dist: flake8 (>=4.0.1) ; extra == 'dev'
Requires-Dist: twine (>=4.0.0) ; extra == 'dev'
